{
  "date": "2026-07-07",
  "cash_position": {
    "improvement": {
      "qb_bank_balance": 29776.63,
      "bank_balance_2657": 11750.99,
      "money_market_2690": 28836.77,
      "total_cash_in_bank": 40587.76,
      "accounts_receivable": 20856.30,
      "cap_one_cc": 10757.50,
      "loc_3705": 14472.26,
      "accounts_payable": 66863.23,
      "net_total": -12623.29
    },
    "restoration": {
      "qb_bank_balance": 5460.12,
      "bank_balance_7363": 10904.43,
      "money_market_2798": 13952.36,
      "total_cash_in_bank": 24856.79,
      "accounts_receivable": 119579.20,
      "loc_5064": 32193.89,
      "cap_one_cc": 33288.05,
      "accounts_payable": 13739.50,
      "net_total": 59770.24
    },
    "combined": {
      "total_cash_in_bank": 65444.55,
      "total_ar": 140435.50,
      "total_ap": 80602.73,
      "credit_debt": 90711.70,
      "net_cash_availability": 29801.17
    }
  },
  "ar": {
    "improvement": [
      {"invoice_num":"33124","client_job":"Manatee County.:681013","balance":1125.74,"invoice_date":"2026-05-20","due_date":"2026-07-04","days_out":48,"expected_payment":"2026-07-04","last_update":"06/12 - work completed, BI Received","division":"improvement"},
      {"invoice_num":"33130","client_job":"Neal Communities:681043","balance":71.90,"invoice_date":"2026-06-05","due_date":"2026-07-04","days_out":32,"expected_payment":"2026-07-04","last_update":"06/05 - Invoice sent","division":"improvement"},
      {"invoice_num":"33131","client_job":"Neal Communities:681043","balance":71.90,"invoice_date":"2026-06-05","due_date":"2026-07-04","days_out":32,"expected_payment":"2026-07-04","last_update":"06/05 - Invoice sent","division":"improvement"},
      {"invoice_num":"33134","client_job":"Custome Craft 681047","balance":13367.77,"invoice_date":"2026-06-17","due_date":"2026-07-16","days_out":20,"expected_payment":"2026-07-16","last_update":"06/17/2026 Inv sent","division":"improvement"},
      {"invoice_num":"33136","client_job":"Taylor Morrison of FL:681045","balance":3329.39,"invoice_date":"2026-06-17","due_date":"2026-07-17","days_out":20,"expected_payment":"2026-07-17","last_update":"06/17 - Invoice created","division":"improvement"},
      {"invoice_num":"33138","client_job":"Taylor Morrison of FL:681049","balance":156.80,"invoice_date":"2026-06-17","due_date":"2026-07-17","days_out":20,"expected_payment":"2026-07-17","last_update":"06/30 - EPO received","division":"improvement"},
      {"invoice_num":"33140","client_job":"Taylor Morrison of FL:681028","balance":1316.24,"invoice_date":"2026-06-22","due_date":"2026-07-22","days_out":15,"expected_payment":"2026-07-22","last_update":"7/6 Pending final work and EPO","division":"improvement"},
      {"invoice_num":"33141","client_job":"Taylor Morrison of FL:681052","balance":1246.56,"invoice_date":"2026-06-25","due_date":"2026-07-25","days_out":12,"expected_payment":"2026-07-25","last_update":"07/02 requested EPO","division":"improvement"},
      {"invoice_num":"33126","client_job":"Dream Finders Homes:681040","balance":170.00,"invoice_date":"2026-05-28","due_date":"2026-06-27","days_out":40,"expected_payment":"2026-06-27","last_update":"07/06 Future orders","division":"improvement"}
    ],
    "restoration": [
      {"invoice_num":"4120","client_job":"Yvonne Badger: 25-0133-MLD","balance":4764.45,"invoice_date":"2025-09-19","due_date":"2025-09-22","days_out":291,"expected_payment":null,"last_update":"IN COLLECTIONS - Last update, Pam spoke to Yvonne and she informed them she is filing for bankrupcy, they still need to confirm with H/O Attorneys and check what type of bankrupcy they are filing to let me know next steps","division":"restoration"},
      {"invoice_num":"4201","client_job":"Kingdom Roofing: 25-0219-MLD","balance":3730.35,"invoice_date":"2025-12-04","due_date":"2025-12-04","days_out":215,"expected_payment":null,"last_update":"No agreement reached as of yet.","division":"restoration"},
      {"invoice_num":"4216","client_job":"Toll Brothers:16257 Wax Myrtle Street-25-0205-STC","balance":850.00,"invoice_date":"2025-12-16","due_date":"2026-01-15","days_out":203,"expected_payment":null,"last_update":"05/05 - AQM is being scheduled but homeowner is not available until the end of July, so still ongoing","division":"restoration"},
      {"invoice_num":"4253","client_job":"Toll Brothers:16257 Wax Myrtle Street-25-0205-STC","balance":6936.52,"invoice_date":"2026-03-31","due_date":"2026-04-30","days_out":98,"expected_payment":null,"last_update":"05/05 - AQM is being scheduled but homeowner is not available until the end of July, so still ongoing","division":"restoration"},
      {"invoice_num":"4317","client_job":"Today's Modern Dentistry:7208 South Beneva Road-26-0066-MLD","balance":3000.00,"invoice_date":"2026-04-30","due_date":"2026-05-30","days_out":68,"expected_payment":"2026-06-12","last_update":"4/30 Invoice created - work ongoing","division":"restoration"},
      {"invoice_num":"4326","client_job":"Choate Constuction:2025 Northeast Pine Island Road-26-0109-WTR","balance":4900.00,"invoice_date":"2026-05-11","due_date":"2026-06-10","days_out":57,"expected_payment":"2026-06-10","last_update":"06/29 - Spoke to AP, check is being released this wednesday","division":"restoration"},
      {"invoice_num":"4331","client_job":"Today's Modern Dentistry:7208 South Beneva Road-26-0066-MLD","balance":950.00,"invoice_date":"2026-05-14","due_date":"2026-05-14","days_out":54,"expected_payment":"2026-05-14","last_update":"06/26 - Ryan texted saying the agreement was to pay upon completion, I reminded him about our conversation for invoicing.","division":"restoration"},
      {"invoice_num":"4345","client_job":"Alon Luxury Apartment Homes:Units 108, 208, 110, 112 and 210 - 2351 University Parkway-26-0127-ESR","balance":17322.85,"invoice_date":"2026-05-28","due_date":"2026-06-27","days_out":40,"expected_payment":"2026-06-27","last_update":"06/29 - Spoke to Brenda she is checking with their Construction team in charge of payment, is the same company just different division","division":"restoration"},
      {"invoice_num":"4346","client_job":"Neal Communities:10213 Canaveral Circle-26-0100-CLN","balance":4590.00,"invoice_date":"2026-05-29","due_date":"2026-06-28","days_out":39,"expected_payment":"2026-07-10","last_update":"06/29 - Jacob to speak to Josh","division":"restoration"},
      {"invoice_num":"4347","client_job":"Manatee County  - Customer:600 301 Boulevard West Suite 202-26-0132-ESR","balance":1816.67,"invoice_date":"2026-05-29","due_date":"2026-07-17","days_out":39,"expected_payment":"2026-07-17","last_update":"05/29 - Invoice created","division":"restoration"},
      {"invoice_num":"4350","client_job":"Today's Modern Dentistry:7208 South Beneva Road-26-0066-MLD","balance":9250.00,"invoice_date":"2026-06-05","due_date":"2026-06-05","days_out":32,"expected_payment":"2026-06-26","last_update":"06/26 - Ryan texted saying the agreement was to pay upon completion, I reminded him about our conversation for invoicing.","division":"restoration"},
      {"invoice_num":"4352","client_job":"Alon Luxury Apartment Homes:Units 108, 208, 110, 112 and 210 - 2351 University Parkway-26-0127-ESR","balance":14041.80,"invoice_date":"2026-06-05","due_date":"2026-07-05","days_out":32,"expected_payment":"2026-07-05","last_update":"06/29 - Spoke to Brenda she is checking with their Construction team in charge of payment, is the same company just different division","division":"restoration"},
      {"invoice_num":"4359","client_job":"Neal Communities:217 Ortelle Terrace-26-0128-MLD","balance":1813.00,"invoice_date":"2026-06-15","due_date":"2026-07-15","days_out":22,"expected_payment":"2026-07-15","last_update":"6/15 Inv created","division":"restoration"},
      {"invoice_num":"4360","client_job":"Dream Finders Homes:7429 Sea Manatee Street-26-0160-WTR","balance":199.00,"invoice_date":"2026-06-16","due_date":"2026-07-16","days_out":21,"expected_payment":"2026-07-16","last_update":"6/30 - EPO Fully approved","division":"restoration"},
      {"invoice_num":"4362","client_job":"Taylor Morrison Florida:Taylor Morrison North:15045 Cuzcorro Court-26-0115-TMP","balance":2877.08,"invoice_date":"2026-06-17","due_date":"2026-07-17","days_out":20,"expected_payment":"2026-07-17","last_update":"06/24 - Brook working on EPO","division":"restoration"},
      {"invoice_num":"4361","client_job":"Neal Communities - Warrany:14351 Skipping Stone Loop-26-0148-WTR","balance":299.00,"invoice_date":"2026-06-17","due_date":"2026-07-17","days_out":20,"expected_payment":"2026-07-17","last_update":"06/17 - Invoice created","division":"restoration"},
      {"invoice_num":"4363","client_job":"Taylor Morrison Tampa:746 Steel Drive-26-0145-WTR","balance":2734.05,"invoice_date":"2026-06-17","due_date":"2026-07-17","days_out":20,"expected_payment":"2026-07-17","last_update":"6/29 EPO fully approved","division":"restoration"},
      {"invoice_num":"4364","client_job":"Taylor Morrison:15169 Cuzcorro Court-26-0159-MLD","balance":1608.33,"invoice_date":"2026-06-17","due_date":"2026-07-17","days_out":20,"expected_payment":"2026-07-17","last_update":"06/17 - Invoice created","division":"restoration"},
      {"invoice_num":"4365","client_job":"Dream Finders Homes:7453 Sea Manatee Street-26-0089-MLD","balance":299.00,"invoice_date":"2026-06-19","due_date":"2026-07-19","days_out":18,"expected_payment":"2026-07-19","last_update":"06/30 - EPO submitted","division":"restoration"},
      {"invoice_num":"4367","client_job":"Neal Communities - Warranty:10041 Hammock Brook Drive-26-0164-WTR","balance":125.00,"invoice_date":"2026-06-19","due_date":"2026-07-19","days_out":18,"expected_payment":"2026-07-19","last_update":"06/19 - Invoice created","division":"restoration"},
      {"invoice_num":"4368","client_job":"Pulte Homes Corporation:4715 Corsair Bay Glen-26-0153-WTR","balance":9000.00,"invoice_date":"2026-06-22","due_date":"2026-07-22","days_out":15,"expected_payment":"2026-07-22","last_update":"06/29 - Invoice adjusted and resent","division":"restoration"},
      {"invoice_num":"4369","client_job":"Neal Communities:140 Corserra Drive-26-0165-STC","balance":250.00,"invoice_date":"2026-06-22","due_date":"2026-07-22","days_out":15,"expected_payment":"2026-07-22","last_update":"06/22 - Invoice created","division":"restoration"},
      {"invoice_num":"4370","client_job":"Pulte Group:5822 Talon Preserve Drive-26-0162-WTR","balance":2517.98,"invoice_date":"2026-06-22","due_date":"2026-07-22","days_out":15,"expected_payment":"2026-07-22","last_update":"06/22 - Invoice created","division":"restoration"},
      {"invoice_num":"4371","client_job":"Neal Communities:10213 Canaveral Circle-26-0100-CLN","balance":8315.00,"invoice_date":"2026-06-24","due_date":"2026-07-24","days_out":13,"expected_payment":"2026-07-24","last_update":"06/24 - Invoice created","division":"restoration"},
      {"invoice_num":"4373","client_job":"Neal Communities - Warranty:6285 Dry Tortugas Drive-26-0168-MLD","balance":125.00,"invoice_date":"2026-06-29","due_date":"2026-07-29","days_out":8,"expected_payment":"2026-07-29","last_update":"06/29 - Invoice created","division":"restoration"},
      {"invoice_num":"4374","client_job":"Neal Communities - Warranty:6492 Big Bayou Dr-26-0172-MLD","balance":125.00,"invoice_date":"2026-06-29","due_date":"2026-07-29","days_out":8,"expected_payment":"2026-07-29","last_update":"06/29 - Invoice created","division":"restoration"},
      {"invoice_num":"4375","client_job":"Neal Communities - Warranty:10117 Crystal Isles Circle-26-0166-WTR","balance":300.00,"invoice_date":"2026-06-29","due_date":"2026-07-29","days_out":8,"expected_payment":"2026-07-29","last_update":"06/29 - Invoice created","division":"restoration"},
      {"invoice_num":"4377","client_job":"Neal Communities - Warranty:8536 Anthirium Loop-26-0178-WTR","balance":2427.00,"invoice_date":"2026-06-30","due_date":"2026-07-30","days_out":7,"expected_payment":"2026-07-30","last_update":"06/30 - Invoice created","division":"restoration"},
      {"invoice_num":"4378","client_job":"Pulte Homes Corporation:14715 Eagle Branch Drive-26-0161-ESR","balance":4797.13,"invoice_date":"2026-06-26","due_date":"2026-07-26","days_out":7,"expected_payment":"2026-07-26","last_update":"06/30 - Invoice created","division":"restoration"},
      {"invoice_num":"4379","client_job":"Neal Communities - Warranty:2630 Paradise Plum Drive-26-0155-CLN","balance":579.60,"invoice_date":"2026-06-30","due_date":"2026-07-30","days_out":7,"expected_payment":"2026-07-30","last_update":"06/30 - Invoice created","division":"restoration"},
      {"invoice_num":"4380","client_job":"Neal Communities - Warranty:2638 Paradise Plum Drive-26-0157-CLN","balance":819.00,"invoice_date":"2026-06-30","due_date":"2026-07-30","days_out":7,"expected_payment":"2026-07-30","last_update":"06/30 - Invoice created","division":"restoration"},
      {"invoice_num":"4381","client_job":"Neal Communities - Warranty:2634 Paradise Plum Drive-26-0156-CLN","balance":960.75,"invoice_date":"2026-06-30","due_date":"2026-07-30","days_out":7,"expected_payment":"2026-07-30","last_update":"06/30 - Invoice created","division":"restoration"},
      {"invoice_num":"4382","client_job":"Neal Communities - Warranty:2626 Paradise Plum Drive-26-0173-CLN","balance":664.65,"invoice_date":"2026-06-30","due_date":"2026-07-30","days_out":7,"expected_payment":"2026-07-30","last_update":"06/30 - Invoice created","division":"restoration"},
      {"invoice_num":"4383","client_job":"Neal Communities - Warranty:2622 Paradise Plum Drive-26-0174-CLN","balance":560.70,"invoice_date":"2026-06-30","due_date":"2026-07-30","days_out":7,"expected_payment":"2026-07-30","last_update":"06/30 - Invoice created","division":"restoration"},
      {"invoice_num":"4384","client_job":"Neal Communities - Warranty:2635 Paradise Plum Drive-26-0176-CLN","balance":403.20,"invoice_date":"2026-06-30","due_date":"2026-07-30","days_out":7,"expected_payment":"2026-07-30","last_update":"06/30 - Invoice created","division":"restoration"},
      {"invoice_num":"4385","client_job":"Neal Communities - Warranty:2639 Paradise Plum Drive-26-0158-CLN","balance":337.05,"invoice_date":"2026-06-30","due_date":"2026-07-30","days_out":7,"expected_payment":"2026-07-30","last_update":"06/30 - Invoice created","division":"restoration"},
      {"invoice_num":"4386","client_job":"Taylor Morrison Florida:Taylor Morrison North:3130 Torta Court-26-0177-CLN","balance":392.00,"invoice_date":"2026-06-30","due_date":"2026-07-30","days_out":7,"expected_payment":"2026-07-30","last_update":"06/30 - Invoice created","division":"restoration"},
      {"invoice_num":"4387","client_job":"Taylor Morrison Tampa:6067 Whetstone Court-26-0151-MLD","balance":4898.04,"invoice_date":"2026-06-30","due_date":"2026-07-30","days_out":7,"expected_payment":"2026-07-30","last_update":"06/30 - Invoice created","division":"restoration"}
    ]
  },
  "ap": {
    "improvement": [
      {"inv_date":"2025-05-07","vendor":"Kingdom Restoration","invoice_num":"299-1","amount":25138.00,"billed":29740.54,"profit_pct":0.155,"approval_status":"680934 - Invoices #32991 $3,748.24, #33000 $10,000, #33019 $15,992.30 ALL PAID","job_total":29740.54,"due_date":"2025-06-06","pay_friday":"Yes","division":"improvement"},
      {"inv_date":"2025-05-28","vendor":"Empire Today LLC","invoice_num":"InvPRJ002738508","amount":9891.99,"billed":15827.18,"profit_pct":0.375,"approval_status":"RT Moore:25-0030-REP/Job 680939 LVT","job_total":585711.47,"due_date":"2025-06-27","pay_friday":"Yes","division":"improvement"},
      {"inv_date":"2026-04-20","vendor":"Amir Shoufany","invoice_num":"73","amount":1600.00,"billed":null,"profit_pct":null,"approval_status":"Pending - 681025 - Outside repairs.","job_total":null,"due_date":"2026-05-04","pay_friday":"Yes","division":"improvement"},
      {"inv_date":"2026-04-27","vendor":"Amir Shoufany","invoice_num":"74","amount":800.00,"billed":null,"profit_pct":null,"approval_status":"Pending - 681025 - Outside repairs.","job_total":null,"due_date":"2026-05-11","pay_friday":"Yes","division":"improvement"},
      {"inv_date":"2026-05-07","vendor":"Amir Shoufany","invoice_num":"80","amount":800.00,"billed":null,"profit_pct":null,"approval_status":"Pending - 681025 - Outside repairs.","job_total":null,"due_date":"2026-05-21","pay_friday":"Yes","division":"improvement"},
      {"inv_date":"2026-06-01","vendor":"Strada","invoice_num":"418453431","amount":7460.14,"billed":null,"profit_pct":null,"approval_status":"Pending - 680939","job_total":588581.42,"due_date":"2026-07-01","pay_friday":"Yes","division":"improvement"},
      {"inv_date":"2026-06-06","vendor":"Harold Bronson","invoice_num":"10005","amount":7250.00,"billed":10875.00,"profit_pct":0.333,"approval_status":"681021 - Invoice 33127 $11,011.38","job_total":16940.58,"due_date":"2026-07-05","pay_friday":"Yes","division":"improvement"},
      {"inv_date":"2026-06-06","vendor":"Harold Bronson","invoice_num":"10018","amount":9943.72,"billed":14915.58,"profit_pct":0.333,"approval_status":"681047 - Invoice #33134 $13,367.77","job_total":14853.08,"due_date":"2026-07-05","pay_friday":"Yes","division":"improvement"},
      {"inv_date":"2026-06-16","vendor":"Amir Shoufany","invoice_num":"84","amount":1980.00,"billed":3168.00,"profit_pct":0.375,"approval_status":"681045 - Invoice 33136 $3,397.34","job_total":3397.34,"due_date":"2026-06-30","pay_friday":"Yes","division":"improvement"},
      {"inv_date":"2026-06-19","vendor":"Damm Good","invoice_num":"9329387512","amount":371.00,"billed":556.50,"profit_pct":0.333,"approval_status":"681013 - Invoice $1,125.74","job_total":1125.74,"due_date":"2026-07-18","pay_friday":"No","division":"improvement"},
      {"inv_date":"2026-06-24","vendor":"XElent Remodeling LLC","invoice_num":"599","amount":795.00,"billed":1272.00,"profit_pct":0.375,"approval_status":"681052 - Invoice 33141 $1,272.00","job_total":1272.00,"due_date":"2026-07-09","pay_friday":"No","division":"improvement"},
      {"inv_date":"2026-06-24","vendor":"XElent Remodeling LLC","invoice_num":"600","amount":285.43,"billed":456.68,"profit_pct":0.375,"approval_status":"681051 - Invoice 33142 $898.00","job_total":898.00,"due_date":"2026-07-09","pay_friday":"No","division":"improvement"},
      {"inv_date":"2026-06-25","vendor":"Amir Shoufany","invoice_num":"88","amount":547.95,"billed":null,"profit_pct":null,"approval_status":"Pending - 681025 - Outside repairs.","job_total":null,"due_date":"2026-07-10","pay_friday":"No","division":"improvement"}
    ],
    "restoration": [
      {"inv_date":"2025-12-16","vendor":"ECO Mold Testing","invoice_num":"9925","amount":5335.00,"billed":8536.00,"profit_pct":0.375,"approval_status":"25-0131-WTR - Invoice #4217 $11,202.00","job_total":11202.00,"due_date":"2026-01-15","pay_friday":"Yes","division":"restoration"},
      {"inv_date":"2026-02-23","vendor":"ECO Mold Testing","invoice_num":"10396","amount":1930.00,"billed":1800.00,"profit_pct":-0.072,"approval_status":"26-0044-MLD - Invoice #4261 $1,800","job_total":1800.00,"due_date":"2026-03-25","pay_friday":"No","division":"restoration"},
      {"inv_date":"2026-05-04","vendor":"Clean Sweep","invoice_num":"15366","amount":1775.00,"billed":2840.00,"profit_pct":0.375,"approval_status":"26-0066-MLD - Invoice #4305 $5,250 - Invoice #4350 $9,250","job_total":17500.00,"due_date":"2026-06-03","pay_friday":"Yes","division":"restoration"},
      {"inv_date":"2026-05-21","vendor":"Clean Sweep","invoice_num":"15492","amount":2510.00,"billed":3765.00,"profit_pct":0.333,"approval_status":"26-0100-CLN - Invoice #4346 $4,590","job_total":4590.00,"due_date":"2026-06-20","pay_friday":"Yes","division":"restoration"},
      {"inv_date":"2026-06-01","vendor":"Damm Good","invoice_num":"9329387084","amount":219.50,"billed":329.25,"profit_pct":0.333,"approval_status":"26-0066-MLD - Invoice #4305 $5,250 - Invoice #4350 $9,250","job_total":17500.00,"due_date":"2026-07-01","pay_friday":"Yes","division":"restoration"},
      {"inv_date":"2026-06-09","vendor":"Clean Sweep","invoice_num":"15608","amount":870.00,"billed":1392.00,"profit_pct":0.375,"approval_status":"26-0143-CLN - Invoice #4356 $1,752.00","job_total":1752.00,"due_date":"2026-07-08","pay_friday":"No","division":"restoration"},
      {"inv_date":"2026-06-11","vendor":"Clean Sweep","invoice_num":"15622","amount":1100.00,"billed":null,"profit_pct":null,"approval_status":"Pending - 26-0131-MLD","job_total":null,"due_date":"2026-07-11","pay_friday":"No","division":"restoration"}
    ]
  },
  "transactions": [
    {"trans_date":"2026-07-04","posted_date":"2026-07-06","card_desc":"John 2671","vendor":"Abode","amount":19.99,"explanation":"Abode","approved_by":"","txn_type":"debit","account":"Capital One – Construction (2897)","division":"improvement"},
    {"trans_date":"2026-07-03","posted_date":"2026-07-04","card_desc":"John 2897","vendor":"Company Cam","amount":99.00,"explanation":"Company Cam","approved_by":"","txn_type":"debit","account":"Capital One – Restoration","division":"restoration"},
    {"trans_date":"2026-07-05","posted_date":"2026-07-07","card_desc":"DDA CHECK 0000000233","vendor":"","amount":1045.00,"explanation":"Clean Sweep Payment","approved_by":"","txn_type":"debit","account":"Restoration Checking – 7363","division":"restoration"},
    {"trans_date":"2026-07-05","posted_date":"2026-07-07","card_desc":"DDA CHECK 0000000232","vendor":"","amount":1570.00,"explanation":"Clean Sweep Payment","approved_by":"","txn_type":"debit","account":"Restoration Checking – 7363","division":"restoration"},
    {"trans_date":"2026-07-05","posted_date":"2026-07-07","card_desc":"DDA CHECK 0000000230","vendor":"","amount":385.00,"explanation":"Clean Sweep Payment","approved_by":"","txn_type":"debit","account":"Restoration Checking – 7363","division":"restoration"},
    {"trans_date":"2026-07-05","posted_date":"2026-07-07","card_desc":"DDA CHECK 0000000229","vendor":"","amount":1535.00,"explanation":"Clean Sweep Payment","approved_by":"","txn_type":"debit","account":"Restoration Checking – 7363","division":"restoration"},
    {"trans_date":"2026-07-05","posted_date":"2026-07-06","card_desc":"INS. PREM AUTO-OWNERS","vendor":"","amount":5116.25,"explanation":"Insurance","approved_by":"","txn_type":"debit","account":"Restoration Checking – 7363","division":"restoration"},
    {"trans_date":"2026-07-05","posted_date":"2026-07-06","card_desc":"MNTHLY FEE Paymode-X 070626","vendor":"","amount":681.31,"explanation":"Referral fees","approved_by":"","txn_type":"debit","account":"Restoration Checking – 7363","division":"restoration"}
  ],
  "brief": [
    {"icon":"💰","category":"Cash Position","message":"Total cash at $65,445, up $6,344 from $59,101 on 07/03. Improvement jumped to $40,588 (+$7,788) as TM payments for #33135 ($8,134), #33142 ($880), and #33144 ($118) cleared over the holiday weekend — $9,131 in collections offset by minor charges. Restoration dropped to $24,857 (−$1,445) as 7363 absorbed insurance $5,116, Paymode-X referral fees $681, and four Clean Sweep checks ($4,535), partially offset by the TM Summit Glen #4366 collection ($3,090)."},
    {"icon":"🔴","category":"Improvement — Negative Net Position","message":"Improvement net total is −$12,623. Cash $40,588 vs AP $66,863. Friday AP marked Yes totals ~$64,463 (Kingdom Restoration $25,138, Empire Today $9,892, Bronson $17,194, Amir #73/#74/#80/#84 $5,180, Strada $7,460). With 2657 at $11,751 and MM at $28,837, Improvement can cover via MM transfer but doing so would drain the division. Recommend releasing Empire Today, Bronson, and Amir items this week; hold Kingdom Restoration $25,138 and Strada $7,460 until Custom Craft #33134 ($13,368, due 07/16) or Choate ($4,900) lands."},
    {"icon":"🟡","category":"Restoration — Insurance and Fees Hit Hard","message":"Restoration absorbed a large Auto-Owners insurance premium ($5,116.25) and Paymode-X referral fees ($681.31) this period, bringing 7363 checking to $10,904. Restoration net remains healthy at $59,770. Friday-marked Restoration AP: ECO Mold $5,335, Clean Sweep $1,775+$2,510, Damm Good $219.50 = $9,839.50 — confirm sufficient AR collections arrive before this Friday."},
    {"icon":"📥","category":"Improvement AR — Priority Collections","message":"Custom Craft #33134 ($13,368, 20d, due 07/16) is the most important Improvement AR item this week. TM #33136 ($3,329, 20d, due 07/17) and TM #33141 ($1,247, 12d, EPO requested 07/02) are the next items. TM #33140 ($1,316) is pending final work and EPO until 07/06 — follow up today."},
    {"icon":"📥","category":"Restoration AR — Priority Collections","message":"Alon Luxury — #4345 ($17,323, 40d overdue) and #4352 ($14,042, 32d, past due 07/05) — Brenda is checking with their Construction team; $31,365 combined, now the most overdue Restoration receivable. Choate Construction #4326 ($4,900, 57d) — check promised for Wednesday 07/01, now 6 days late; escalate immediately. Today's Modern Dentistry #4350 ($9,250, 32d) and #4331 ($950, 54d) — payment terms dispute unresolved. Pulte #4368 ($9,000, 15d) — awaiting response to adjusted invoice. TM Tampa #4363 ($2,734, EPO approved 06/29) and TM Cuzcorro #4362 ($2,877, Brook working on EPO) — follow up for payment."},
    {"icon":"⚠️","category":"Net Availability Adjustment","message":"Net Cash Availability of $29,801 excludes Yvonne Badger ($4,764.45, in collections/bankruptcy). This exclusion is also applied to debt paydown recommendations."},
    {"icon":"🔴","category":"Credit — Cap One Restoration Critical","message":"Cap One Restoration at 87.6% ($33,288 of $38K) — remains at a critical level. Company Cam $99 added over the weekend. A paydown of $5K+ from Restoration MM is urgently needed. Do not approve further large charges to Cap One Restoration until this is addressed. Cap One Construction at 23.9% ($10,758 of $45K, Abode $20 added). LOC 3705 $14,472 (14.5%), LOC 5064 $32,194 (42.9%)."}
  ]
}
